odoo10_addon_account_asset_management-10.0.3.1.0.99.dev54-py3.8-nspkg.pth
odoo/addons/account_asset_management/README.rst
odoo/addons/account_asset_management/__init__.py
odoo/addons/account_asset_management/__manifest__.py
odoo/addons/account_asset_management/i18n/account_asset.pot
odoo/addons/account_asset_management/i18n/account_asset_management.pot
odoo/addons/account_asset_management/i18n/am.po
odoo/addons/account_asset_management/i18n/ar.po
odoo/addons/account_asset_management/i18n/bg.po
odoo/addons/account_asset_management/i18n/bs.po
odoo/addons/account_asset_management/i18n/ca.po
odoo/addons/account_asset_management/i18n/ca_ES.po
odoo/addons/account_asset_management/i18n/cs.po
odoo/addons/account_asset_management/i18n/da.po
odoo/addons/account_asset_management/i18n/de.po
odoo/addons/account_asset_management/i18n/el_GR.po
odoo/addons/account_asset_management/i18n/en_AU.po
odoo/addons/account_asset_management/i18n/en_GB.po
odoo/addons/account_asset_management/i18n/es.po
odoo/addons/account_asset_management/i18n/es_AR.po
odoo/addons/account_asset_management/i18n/es_CL.po
odoo/addons/account_asset_management/i18n/es_CO.po
odoo/addons/account_asset_management/i18n/es_CR.po
odoo/addons/account_asset_management/i18n/es_DO.po
odoo/addons/account_asset_management/i18n/es_EC.po
odoo/addons/account_asset_management/i18n/es_ES.po
odoo/addons/account_asset_management/i18n/es_MX.po
odoo/addons/account_asset_management/i18n/es_PE.po
odoo/addons/account_asset_management/i18n/es_PY.po
odoo/addons/account_asset_management/i18n/es_VE.po
odoo/addons/account_asset_management/i18n/et.po
odoo/addons/account_asset_management/i18n/eu.po
odoo/addons/account_asset_management/i18n/fa.po
odoo/addons/account_asset_management/i18n/fi.po
odoo/addons/account_asset_management/i18n/fr.po
odoo/addons/account_asset_management/i18n/fr_BE.po
odoo/addons/account_asset_management/i18n/fr_CA.po
odoo/addons/account_asset_management/i18n/fr_CH.po
odoo/addons/account_asset_management/i18n/fr_FR.po
odoo10_addon_account_asset_management-10.0.3.1.0.99.dev54.dist-info/METADATA
odoo10_addon_account_asset_management-10.0.3.1.0.99.dev54.dist-info/WHEEL
odoo10_addon_account_asset_management-10.0.3.1.0.99.dev54.dist-info/namespace_packages.txt
odoo10_addon_account_asset_management-10.0.3.1.0.99.dev54.dist-info/top_level.txt
odoo10_addon_account_asset_management-10.0.3.1.0.99.dev54.dist-info/RECORD
