Metadata-Version: 2.1
Name: odoo10-addon-account-asset-management
Version: 10.0.3.1.0.99.dev54
Summary: Assets Management
Home-page: http://www.noviat.com
Author: Noviat,Odoo Community Association (OCA)
Author-email: support@odoo-community.org
License: AGPL-3
Platform: UNKNOWN
Classifier: Programming Language :: Python
Classifier: Framework :: Odoo
Classifier: Framework :: Odoo :: 10.0
Classifier: License :: OSI Approved :: GNU Affero General Public License v3
Requires-Python: ~=2.7
Requires-Dist: odoo10-addon-account-fiscal-year
Requires-Dist: odoo <10.1dev,>=10.0
